{"nodes":[{"id":115985,"label":"Barre Phillips","size":5,"color":{"r":192,"g":0,"b":64}},{"id":585092,"label":"Dave Holland","size":1,"color":{"r":192,"g":0,"b":64}},{"id":189180,"label":"John Surman","size":1,"color":{"r":192,"g":0,"b":64}},{"id":214546,"label":"John Abercrombie","size":1,"color":{"r":192,"g":0,"b":64}},{"id":630658,"label":"Stu Martin","size":1,"color":{"r":192,"g":0,"b":64}},{"id":21129,"label":"Trilok Gurtu","size":1,"color":{"r":192,"g":0,"b":64}},{"id":23566,"label":"Terje Rypdal","size":1,"color":{"r":192,"g":0,"b":64}}],"edges":[{"target":"115985","label":"Music from Two Basses","source":585092},{"target":"115985","label":"Mountainscapes","source":189180},{"target":"115985","label":"Mountainscapes","source":214546},{"target":"115985","label":"Mountainscapes","source":630658},{"target":"115985","label":"Journal Violone II","source":189180},{"target":"115985","label":"Three Day Moon","source":21129},{"target":"115985","label":"Three Day Moon","source":23566}]}